{
  "meta": {
    "base": "http://localhost:8000",
    "reps": 15,
    "network": {
      "latencyMs": 150,
      "downloadMbps": 1.5,
      "uploadMbps": 0.75
    },
    "cpuThrottlingRate": 4,
    "timestamp": "2025-10-20T19:34:27.418Z"
  },
  "scenario": "content",
  "variant": "I2",
  "runs": [
    {
      "rep": 1,
      "INP": 24,
      "INP_W": 1.600000023841858,
      "INP_H": 0,
      "INP_R": 22.399999976158142,
      "LoAFsum": 226,
      "LoAFcount": 1,
      "LoAFsum_500ms": 0,
      "LoAFcount_500ms": 0,
      "LoAFany_500ms": 0
    },
    {
      "rep": 2,
      "INP": 24,
      "INP_W": 1.300000011920929,
      "INP_H": 0,
      "INP_R": 22.69999998807907,
      "LoAFsum": 254,
      "LoAFcount": 1,
      "LoAFsum_500ms": 0,
      "LoAFcount_500ms": 0,
      "LoAFany_500ms": 0
    },
    {
      "rep": 3,
      "INP": 24,
      "INP_W": 1.600000023841858,
      "INP_H": 0,
      "INP_R": 22.399999976158142,
      "LoAFsum": 253.20000004768372,
      "LoAFcount": 1,
      "LoAFsum_500ms": 0,
      "LoAFcount_500ms": 0,
      "LoAFany_500ms": 0
    },
    {
      "rep": 4,
      "INP": 24,
      "INP_W": 0.699999988079071,
      "INP_H": 0,
      "INP_R": 23.30000001192093,
      "LoAFsum": 253,
      "LoAFcount": 1,
      "LoAFsum_500ms": 0,
      "LoAFcount_500ms": 0,
      "LoAFany_500ms": 0
    },
    {
      "rep": 5,
      "INP": 40,
      "INP_W": 1.0999999642372131,
      "INP_H": 0,
      "INP_R": 38.90000003576279,
      "LoAFsum": 252.30000001192093,
      "LoAFcount": 1,
      "LoAFsum_500ms": 0,
      "LoAFcount_500ms": 0,
      "LoAFany_500ms": 0
    },
    {
      "rep": 6,
      "INP": 32,
      "INP_W": 1.199999988079071,
      "INP_H": 0,
      "INP_R": 30.80000001192093,
      "LoAFsum": 253.5,
      "LoAFcount": 1,
      "LoAFsum_500ms": 0,
      "LoAFcount_500ms": 0,
      "LoAFany_500ms": 0
    },
    {
      "rep": 7,
      "INP": 24,
      "INP_W": 1.199999988079071,
      "INP_H": 0,
      "INP_R": 22.80000001192093,
      "LoAFsum": 253.89999997615814,
      "LoAFcount": 1,
      "LoAFsum_500ms": 0,
      "LoAFcount_500ms": 0,
      "LoAFany_500ms": 0
    },
    {
      "rep": 8,
      "INP": 24,
      "INP_W": 0.800000011920929,
      "INP_H": 0,
      "INP_R": 23.19999998807907,
      "LoAFsum": 262.2000000476837,
      "LoAFcount": 1,
      "LoAFsum_500ms": 0,
      "LoAFcount_500ms": 0,
      "LoAFany_500ms": 0
    },
    {
      "rep": 9,
      "INP": 40,
      "INP_W": 0.19999998807907104,
      "INP_H": 0.9000000357627869,
      "INP_R": 38.89999997615814,
      "LoAFsum": 252.9000000357628,
      "LoAFcount": 1,
      "LoAFsum_500ms": 0,
      "LoAFcount_500ms": 0,
      "LoAFany_500ms": 0
    },
    {
      "rep": 10,
      "INP": 40,
      "INP_W": 1.5999999642372131,
      "INP_H": 0.10000002384185791,
      "INP_R": 38.30000001192093,
      "LoAFsum": 253.70000004768372,
      "LoAFcount": 1,
      "LoAFsum_500ms": 0,
      "LoAFcount_500ms": 0,
      "LoAFany_500ms": 0
    },
    {
      "rep": 11,
      "INP": 24,
      "INP_W": 1.2999999523162842,
      "INP_H": 0,
      "INP_R": 22.700000047683716,
      "LoAFsum": 254.30000001192093,
      "LoAFcount": 1,
      "LoAFsum_500ms": 0,
      "LoAFcount_500ms": 0,
      "LoAFany_500ms": 0
    },
    {
      "rep": 12,
      "INP": 24,
      "INP_W": 1,
      "INP_H": 0,
      "INP_R": 23,
      "LoAFsum": 254.19999998807907,
      "LoAFcount": 1,
      "LoAFsum_500ms": 0,
      "LoAFcount_500ms": 0,
      "LoAFany_500ms": 0
    },
    {
      "rep": 13,
      "INP": 24,
      "INP_W": 1.199999988079071,
      "INP_H": 0,
      "INP_R": 22.80000001192093,
      "LoAFsum": 254.5,
      "LoAFcount": 1,
      "LoAFsum_500ms": 0,
      "LoAFcount_500ms": 0,
      "LoAFany_500ms": 0
    },
    {
      "rep": 14,
      "INP": 24,
      "INP_W": 1.5,
      "INP_H": 0,
      "INP_R": 22.5,
      "LoAFsum": 259.69999998807907,
      "LoAFcount": 1,
      "LoAFsum_500ms": 0,
      "LoAFcount_500ms": 0,
      "LoAFany_500ms": 0
    },
    {
      "rep": 15,
      "INP": 24,
      "INP_W": 0.699999988079071,
      "INP_H": 0,
      "INP_R": 23.30000001192093,
      "LoAFsum": 262,
      "LoAFcount": 1,
      "LoAFsum_500ms": 0,
      "LoAFcount_500ms": 0,
      "LoAFany_500ms": 0
    }
  ]
}